jimutmap/__init__.py
jimutmap/file_size.py
jimutmap/jimutmap.py
jimutmap/sanity_checker.py
jimutmap/tiles_sticher.py
jimutmap-1.4.2.dist-info/COPYING
jimutmap-1.4.2.dist-info/LICENSE
jimutmap-1.4.2.dist-info/METADATA
jimutmap-1.4.2.dist-info/WHEEL
jimutmap-1.4.2.dist-info/top_level.txt
jimutmap-1.4.2.dist-info/RECORD
