Metadata-Version: 2.1
Name: jimutmap
Version: 1.4.2
Summary: To get enormous amount of map tiles with ease
Home-page: https://github.com/Jimut123/jimutmap
Author: Jimut Bahan Pal and the Jimutmap Contributors
Author-email: jimutbahanpal@yahoo.com
Classifier: Programming Language :: Python :: 3
Classifier: License :: OSI Approved :: MIT License
Classifier: Operating System :: OS Independent
License-File: LICENSE
License-File: COPYING
Requires-Dist: certifi (==2020.12.5)
Requires-Dist: chardet (==4.0.0)
Requires-Dist: chromedriver-autoinstaller (==0.2.2)
Requires-Dist: idna (==2.10)
Requires-Dist: numpy (==1.19.5)
Requires-Dist: requests (==2.25.1)
Requires-Dist: selenium (==3.141.0)
Requires-Dist: tqdm (==4.53.0)
Requires-Dist: urllib3 (==1.26.5)
Requires-Dist: opencv-python (==4.5.5.64)
